nooverlap-0.2.1.dist-info/METADATA
nooverlap-0.2.1.dist-info/WHEEL
nooverlap/tests/test_example.py
nooverlap/tests/test_pusher.py
nooverlap/matplotlib/push_text.py
nooverlap/matplotlib/__init__.py
nooverlap/__init__.py
nooverlap/nooverlap.cpython-313-aarch64-linux-gnu.so
nooverlap-0.2.1.dist-info/RECORD
